streamlit_lexical/__init__.py
streamlit_lexical/example.py
streamlit_lexical/example2.py
streamlit_lexical/frontend/build/asset-manifest.json
streamlit_lexical/frontend/build/bootstrap.min.css
streamlit_lexical/frontend/build/index.html
streamlit_lexical/frontend/build/static/css/main.71783fd3.css
streamlit_lexical/frontend/build/static/css/main.71783fd3.css.map
streamlit_lexical/frontend/build/static/js/main.e109350d.js
streamlit_lexical/frontend/build/static/js/main.e109350d.js.LICENSE.txt
streamlit_lexical/frontend/build/static/js/main.e109350d.js.map
streamlit_lexical/frontend/build/static/media/arrow-clockwise.2ba775456dd603357519.svg
streamlit_lexical/frontend/build/static/media/arrow-counterclockwise.48745dc8e6d9b1a2f8ec.svg
streamlit_lexical/frontend/build/static/media/type-bold.b3bec3f33045771f9484.svg
streamlit_lexical/frontend/build/static/media/type-italic.d3971b39b0fe39a09b1b.svg
streamlit_lexical/frontend/build/static/media/type-underline.b41f84ace38d530f30b9.svg
streamlit_lexical-1.3.0.dist-info/licenses/LICENSE
streamlit_lexical-1.3.0.dist-info/METADATA
streamlit_lexical-1.3.0.dist-info/WHEEL
streamlit_lexical-1.3.0.dist-info/top_level.txt
streamlit_lexical-1.3.0.dist-info/RECORD
